{
	"info": {
		"_postman_id": "c7cc8dc3-2279-47a2-8dfd-7181bdd888e2",
		"name": "Weather",
		"schema": "https://schema.getpostman.com/json/collection/v2.0.0/collection.json",
		"_exporter_id": "31556302"
	},
	"item": [
		{
			"name": "GetWeatherByCoords",
			"request": {
				"method": "GET",
				"header": []
			},
			"response": []
		},
		{
			"name": "GetWeatherByCityName",
			"request": {
				"method": "GET",
				"header": []
			},
			"response": []
		},
		{
			"name": "GetWeatherByCityId",
			"request": {
				"method": "GET",
				"header": []
			},
			"response": []
		}
	],
	"variable": [
		{
			"key": "weather_api_key",
			"value": "d4cde55b3771d3e97882a32af3b4a774"
		}
	]
}